alibabacloud_credentials/__init__.py
alibabacloud_credentials/client.py
alibabacloud_credentials/credentials.py
alibabacloud_credentials/exceptions.py
alibabacloud_credentials/models.py
alibabacloud_credentials/providers.py
alibabacloud_credentials/http/__init__.py
alibabacloud_credentials/http/_options.py
alibabacloud_credentials/provider/__init__.py
alibabacloud_credentials/provider/cli_profile.py
alibabacloud_credentials/provider/cloud_sso.py
alibabacloud_credentials/provider/default.py
alibabacloud_credentials/provider/ecs_ram_role.py
alibabacloud_credentials/provider/env.py
alibabacloud_credentials/provider/oauth.py
alibabacloud_credentials/provider/oidc.py
alibabacloud_credentials/provider/profile.py
alibabacloud_credentials/provider/ram_role_arn.py
alibabacloud_credentials/provider/refreshable.py
alibabacloud_credentials/provider/rsa_key_pair.py
alibabacloud_credentials/provider/static_ak.py
alibabacloud_credentials/provider/static_sts.py
alibabacloud_credentials/provider/uri.py
alibabacloud_credentials/utils/__init__.py
alibabacloud_credentials/utils/auth_constant.py
alibabacloud_credentials/utils/auth_util.py
alibabacloud_credentials/utils/parameter_helper.py
alibabacloud_credentials-1.0.4.dist-info/METADATA
alibabacloud_credentials-1.0.4.dist-info/WHEEL
alibabacloud_credentials-1.0.4.dist-info/top_level.txt
alibabacloud_credentials-1.0.4.dist-info/RECORD
