Metadata-Version: 2.1
Name: alibabacloud-credentials
Version: 1.0.4
Summary: The alibabacloud credentials module of alibabaCloud Python SDK.
Home-page: https://github.com/aliyun/credentials-python
Author: Alibaba Cloud
Author-email: alibaba-cloud-sdk-dev-team@list.alibaba-inc.com
License: Apache License 2.0
Keywords: alibabacloud,sdk,tea
Platform: any
Classifier: Development Status :: 5 - Production/Stable
Classifier: Intended Audience :: Developers
Classifier: License :: OSI Approved :: Apache Software License
Classifier: Programming Language :: Python :: 3
Classifier: Programming Language :: Python :: 3.7
Classifier: Programming Language :: Python :: 3.8
Classifier: Programming Language :: Python :: 3.9
Classifier: Programming Language :: Python :: 3.10
Classifier: Programming Language :: Python :: 3.11
Classifier: Programming Language :: Python :: 3.12
Classifier: Topic :: Software Development
Requires-Python: >=3.7
Requires-Dist: APScheduler (<4.0.0,>=3.10.0)
Requires-Dist: aiofiles (<25.0.0,>=22.1.0)
Requires-Dist: alibabacloud-tea (>=0.4.0)
Requires-Dist: alibabacloud-credentials-api (<2.0.0,>=1.0.0)
